ug4py_plugins_smallstrainmechanics-0.0.1.dist-info/RECORD
ug4py_plugins_smallstrainmechanics-0.0.1.dist-info/WHEEL
ug4py_plugins_smallstrainmechanics-0.0.1.dist-info/METADATA
ug4py_plugins_smallstrainmechanics-0.0.1.dist-info/licenses/LICENSE
ug4py/pysmallstrainmechanics.cpython-312-darwin.so
