Metadata-Version: 2.2
Name: ug4py-plugins-smallstrainmechanics
Version: 0.0.1
Summary: This is UG4-plugin for SmallStrainMechanics.
